<annotation>
	<filename>action0459.jpg</filename>
	<originalfile>2054783032_b81828918d.jpg</originalfile>
	<folder>Willow-actions</folder>
	<source>
		<annotation>Willow-actions</annotation>
		<database>Willow-actions</database>
		<image>flickr</image>
		<flickrid>2054783032</flickrid>
	</source>
	<segmented>0</segmented>
	<size>
		<width>500</width>
		<height>334</height>
		<depth>3</depth>
	</size>
	<object>
		<name>person</name>
		<bndbox>
			<xmin>9</xmin>
			<ymin>35</ymin>
			<xmax>258</xmax>
			<ymax>333</ymax>
		</bndbox>
		<pose>Right</pose>
		<difficult>0</difficult>
		<truncated>1</truncated>
		<occluded>0</occluded>
	</object>
</annotation>
