<annotation>
	<filename>action0464.jpg</filename>
	<originalfile>2193702872_4202893e61.jpg</originalfile>
	<folder>Willow-actions</folder>
	<source>
		<annotation>Willow-actions</annotation>
		<database>Willow-actions</database>
		<image>flickr</image>
		<flickrid>2193702872</flickrid>
	</source>
	<segmented>0</segmented>
	<size>
		<width>453</width>
		<height>500</height>
		<depth>3</depth>
	</size>
	<object>
		<name>person</name>
		<bndbox>
			<xmin>87</xmin>
			<ymin>236</ymin>
			<xmax>271</xmax>
			<ymax>472</ymax>
		</bndbox>
		<pose>Unspecified</pose>
		<difficult>0</difficult>
		<truncated>0</truncated>
		<occluded>0</occluded>
	</object>
	<object>
		<name>person</name>
		<bndbox>
			<xmin>168</xmin>
			<ymin>18</ymin>
			<xmax>305</xmax>
			<ymax>458</ymax>
		</bndbox>
		<pose>Left</pose>
		<difficult>0</difficult>
		<truncated>0</truncated>
		<occluded>0</occluded>
	</object>
	<object>
		<name>person</name>
		<bndbox>
			<xmin>287</xmin>
			<ymin>40</ymin>
			<xmax>436</xmax>
			<ymax>435</ymax>
		</bndbox>
		<pose>Left</pose>
		<difficult>0</difficult>
		<truncated>0</truncated>
		<occluded>0</occluded>
	</object>
</annotation>
