<annotation>
	<filename>action0699.jpg</filename>
	<originalfile>3759418861_29a01d1c8b.jpg</originalfile>
	<folder>Willow-actions</folder>
	<source>
		<annotation>Willow-actions</annotation>
		<database>Willow-actions</database>
		<image>flickr</image>
		<flickrid>3759418861</flickrid>
	</source>
	<segmented>0</segmented>
	<size>
		<width>500</width>
		<height>334</height>
		<depth>3</depth>
	</size>
	<object>
		<name>person</name>
		<bndbox>
			<xmin>274</xmin>
			<ymin>74</ymin>
			<xmax>315</xmax>
			<ymax>251</ymax>
		</bndbox>
		<pose>Unspecified</pose>
		<difficult>0</difficult>
		<truncated>0</truncated>
		<occluded>0</occluded>
	</object>
	<object>
		<name>person</name>
		<bndbox>
			<xmin>228</xmin>
			<ymin>84</ymin>
			<xmax>265</xmax>
			<ymax>271</ymax>
		</bndbox>
		<pose>Left</pose>
		<difficult>0</difficult>
		<truncated>0</truncated>
		<occluded>0</occluded>
	</object>
</annotation>
